nonebot_plugin_exrate/__init__.py
nonebot_plugin_exrate/config.py
nonebot_plugin_exrate-1.0.1.dist-info/METADATA
nonebot_plugin_exrate-1.0.1.dist-info/WHEEL
nonebot_plugin_exrate-1.0.1.dist-info/RECORD
