Metadata-Version: 2.3
Name: nonebot-plugin-exrate
Version: 1.0.1
Summary: 一个Nonebot2插件用于查询各大银行的货币汇率
License: GPL-3.0
Keywords: nonebot2,exchange
Author: Maizi
Author-email: maizicncn@gmail.com
Requires-Python: >=3.8,<4.0
Classifier: License :: OSI Approved :: GNU General Public License v3 (GPLv3)
Classifier: Programming Language :: Python :: 3
Classifier: Programming Language :: Python :: 3.8
Classifier: Programming Language :: Python :: 3.9
Classifier: Programming Language :: Python :: 3.10
Classifier: Programming Language :: Python :: 3.11
Classifier: Programming Language :: Python :: 3.12
Classifier: Programming Language :: Python :: 3.13
Requires-Dist: httpx (>=0.26.0)
Requires-Dist: nonebot-adapter-onebot (>=2.0.0,<3.0.0)
Requires-Dist: nonebot2 (>=2.2.1,<3.0.0)
Project-URL: Documentation, https://github.com/bankcarddev/nonebot-plugin-exrate#readme
Project-URL: Homepage, https://github.com/bankcarddev/nonebot-plugin-exrate
Project-URL: Repository, https://github.com/bankcarddev/nonebot-plugin-exrate
